loadin
