Metadata-Version: 1.0
Name: loadin
Version: 0.1.4
Summary: quite a easy way to apply animation to your function
Home-page: https://github.com/williamfzc/loadin
Author: Feng Zhangchi
Author-email: fengzc@vip.qq.com
License: UNKNOWN
Platform: UNKNOWN
